{
  "db_name": "PostgreSQL",
  "query": "SELECT * FROM garden WHERE id = $1",
  "describe": {
    "columns": [
      {
        "ordinal": 0,
        "name": "id",
        "type_info": "Uuid"
      },
      {
        "ordinal": 1,
        "name": "title",
        "type_info": "Text"
      },
      {
        "ordinal": 2,
        "name": "create_timestamp",
        "type_info": "Timestamptz"
      },
      {
        "ordinal": 3,
        "name": "slug",
        "type_info": "Text"
      },
      {
        "ordinal": 4,
        "name": "update_timestamp",
        "type_info": "Timestamptz"
      }
    ],
    "parameters": {
      "Left": [
        "Uuid"
      ]
    },
    "nullable": [
      false,
      false,
      false,
      false,
      false
    ]
  },
  "hash": "ccdde869acd593b24b537fb2592b6a1c182140f88882d343f2076fb1982b0d5f"
}
